{"Dialogue":{"conditions":{"false":"","true":""},"connects_to":["Dialogue329"],"location":"(-220, 280)","logic":"","size":"(-392.49707, 427, 285.993652, 74)","text":"background=/bureau/"},"Dialogue1804":{"conditions":{"false":"","true":""},"connects_to":["Dialogue1813"],"location":"(2680, 260)","logic":"","size":"(2507.50293, 407, 207, 86)","text":"character=transparent.png"},"Dialogue1813":{"conditions":{"false":"","true":""},"connects_to":["Dialogue820"],"location":"(2920, 280)","logic":"","size":"(2747.50293, 427, 201, 75)","text":"name= "},"Dialogue329":{"conditions":{"false":"","true":""},"connects_to":["Dialogue353"],"location":"(180, 280)","logic":"","size":"(7.50293, 427, 261.999023, 82.999939)","text":"character=adjointe.svg"},"Dialogue338":{"conditions":{"false":"","true":""},"connects_to":["Dialogue347"],"location":"(800, 260)","logic":"","size":"(627.50293, 407, 279.994873, 145)","text":"Vous avez construit votre premier bâtiment !"},"Dialogue347":{"conditions":{"false":"","true":""},"connects_to":["Dialogue362"],"location":"(1160, 260)","logic":"","size":"(987.50293, 407, 259.999023, 150)","text":"Les maisons augmentent la population maximale que votre ville peut accueillir !"},"Dialogue353":{"conditions":{"false":"","true":""},"connects_to":["Dialogue338"],"location":"(540, 280)","logic":"","size":"(367.50293, 427, 227.997314, 108.999939)","text":"name=Adjointe"},"Dialogue362":{"conditions":{"false":"","true":""},"connects_to":["Dialogue372"],"location":"(1540, 240)","logic":"","size":"(1367.50293, 387, 470.997559, 101)","text":"Pour atteindre ce nombre, vous devrez satisfaire les habitants, en construisant certains bâtiments ou grâce aux événements !"},"Dialogue372":{"conditions":{"false":"","true":""},"connects_to":["Dialogue1804"],"location":"(2200, 260)","logic":"","size":"(2027.50293, 407, 462.000244, 102.166626)","text":"Construisons une école ! Cela devrait faire plaisir aux citoyens !"},"Dialogue381":{"conditions":{"false":"","true":""},"connects_to":["End"],"location":"(3460, 260)","logic":"","size":"(3287.50293, 407, 201, 75)","text":"building=Ecole"},"Dialogue820":{"conditions":{"false":"","true":""},"connects_to":["Dialogue381"],"location":"(3140, 280)","logic":"","size":"(2967.50293, 427, 248, 76)","text":"*Vous débloquez l’école !*"},"End":{"conditions":{},"connects_to":{},"location":"(3680, 240)","logic":"","text":""},"Start":{"conditions":{"false":"","true":""},"connects_to":["Dialogue"],"location":"(-460, 280)","logic":"","size":"(-632.49707, 427, 196.994141, 67)","text":""},"info":{"display_name":"","name":""}}
